lightrag/__init__.py
lightrag/base.py
lightrag/exceptions.py
lightrag/lightrag.py
lightrag/llm.py
lightrag/namespace.py
lightrag/operate.py
lightrag/prompt.py
lightrag/types.py
lightrag/utils.py
lightrag/api/__init__.py
lightrag/api/auth.py
lightrag/api/gunicorn_config.py
lightrag/api/lightrag_server.py
lightrag/api/run_with_gunicorn.py
lightrag/api/utils_api.py
lightrag/api/routers/__init__.py
lightrag/api/routers/document_routes.py
lightrag/api/routers/graph_routes.py
lightrag/api/routers/ollama_api.py
lightrag/api/routers/query_routes.py
lightrag/api/webui/index.html
lightrag/api/webui/logo.png
lightrag/api/webui/assets/index-4I5HV9Fr.js
lightrag/api/webui/assets/index-BSOt8Nur.css
lightrag/kg/__init__.py
lightrag/kg/age_impl.py
lightrag/kg/chroma_impl.py
lightrag/kg/faiss_impl.py
lightrag/kg/gremlin_impl.py
lightrag/kg/json_doc_status_impl.py
lightrag/kg/json_kv_impl.py
lightrag/kg/milvus_impl.py
lightrag/kg/mongo_impl.py
lightrag/kg/nano_vector_db_impl.py
lightrag/kg/neo4j_impl.py
lightrag/kg/networkx_impl.py
lightrag/kg/oracle_impl.py
lightrag/kg/postgres_impl.py
lightrag/kg/qdrant_impl.py
lightrag/kg/redis_impl.py
lightrag/kg/shared_storage.py
lightrag/kg/tidb_impl.py
lightrag/llm/__init__.py
lightrag/llm/azure_openai.py
lightrag/llm/bedrock.py
lightrag/llm/hf.py
lightrag/llm/jina.py
lightrag/llm/llama_index_impl.py
lightrag/llm/lmdeploy.py
lightrag/llm/lollms.py
lightrag/llm/nvidia_openai.py
lightrag/llm/ollama.py
lightrag/llm/openai.py
lightrag/llm/siliconcloud.py
lightrag/llm/zhipu.py
lightrag/tools/__init__.py
lightrag/tools/lightrag_visualizer/__init__.py
lightrag/tools/lightrag_visualizer/graph_visualizer.py
lightrag_dembrane-1.2.7.8.dist-info/licenses/LICENSE
lightrag_dembrane-1.2.7.8.dist-info/METADATA
lightrag_dembrane-1.2.7.8.dist-info/WHEEL
lightrag_dembrane-1.2.7.8.dist-info/entry_points.txt
lightrag_dembrane-1.2.7.8.dist-info/top_level.txt
lightrag_dembrane-1.2.7.8.dist-info/RECORD
