Metadata-Version: 2.4
Name: lightrag-dembrane
Version: 1.2.7.8
Summary: LightRAG: Simple and Fast Retrieval-Augmented Generation
Home-page: https://github.com/HKUDS/LightRAG
Author: ZiruiGuo
Project-URL: Documentation, https://github.com/HKUDS/LightRAG
Project-URL: Source, https://github.com/HKUDS/LightRAG
Project-URL: Tracker, https://github.com/HKUDS/LightRAG/issues
Classifier: Development Status :: 4 - Beta
Classifier: Programming Language :: Python :: 3
Classifier: License :: OSI Approved :: MIT License
Classifier: Operating System :: OS Independent
Classifier: Intended Audience :: Developers
Classifier: Topic :: Software Development :: Libraries :: Python Modules
Requires-Python: >=3.9
License-File: LICENSE
Provides-Extra: api
Provides-Extra: tools
Dynamic: author
Dynamic: classifier
Dynamic: description
Dynamic: description-content-type
Dynamic: home-page
Dynamic: license-file
Dynamic: project-url
Dynamic: provides-extra
Dynamic: requires-python
Dynamic: summary
